hep_data_llm/__about__.py
hep_data_llm/__init__.py
hep_data_llm/cli.py
hep_data_llm/direct-query-config.yaml
hep_data_llm/hint_files.py
hep_data_llm/models.py
hep_data_llm/models.yaml
hep_data_llm/plot.py
hep_data_llm/query_code.py
hep_data_llm/query_config.py
hep_data_llm/run_in_docker.py
hep_data_llm/usage_info.py
hep_data_llm/utils.py
hep_data_llm-1.0.0.dist-info/METADATA
hep_data_llm-1.0.0.dist-info/WHEEL
hep_data_llm-1.0.0.dist-info/entry_points.txt
hep_data_llm-1.0.0.dist-info/licenses/LICENSE.txt
hep_data_llm-1.0.0.dist-info/RECORD
