Metadata-Version: 2.4
Name: hep-data-llm
Version: 1.0.0
Project-URL: Documentation, https://github.com/Gordon Watts/hep-data-llm#readme
Project-URL: Issues, https://github.com/Gordon Watts/hep-data-llm/issues
Project-URL: Source, https://github.com/Gordon Watts/hep-data-llm
Author-email: Gordon Watts <gwatts@uw.edu>
License-Expression: MIT
License-File: LICENSE.txt
Classifier: Development Status :: 4 - Beta
Classifier: Programming Language :: Python
Classifier: Programming Language :: Python :: 3.8
Classifier: Programming Language :: Python :: 3.9
Classifier: Programming Language :: Python :: 3.10
Classifier: Programming Language :: Python :: 3.11
Classifier: Programming Language :: Python :: 3.12
Classifier: Programming Language :: Python :: Implementation :: CPython
Classifier: Programming Language :: Python :: Implementation :: PyPy
Requires-Python: >=3.8
Requires-Dist: diskcache
Requires-Dist: dotenv
Requires-Dist: fsspec[http]
Requires-Dist: openai
Requires-Dist: pydantic
Requires-Dist: pyyaml
Requires-Dist: tenacity
Requires-Dist: typer
Provides-Extra: test
Requires-Dist: coverage; extra == 'test'
Requires-Dist: hypothesis; extra == 'test'
Requires-Dist: pytest; extra == 'test'
Requires-Dist: pytest-asyncio; extra == 'test'
Requires-Dist: pytest-cov; extra == 'test'
Requires-Dist: pytest-mock; extra == 'test'
